odoo/addons/account_maturity_date_default/README.rst
odoo/addons/account_maturity_date_default/__init__.py
odoo/addons/account_maturity_date_default/__manifest__.py
odoo/addons/account_maturity_date_default/i18n/account_maturity_date_default.pot
odoo/addons/account_maturity_date_default/i18n/es.po
odoo/addons/account_maturity_date_default/i18n/it.po
odoo/addons/account_maturity_date_default/models/__init__.py
odoo/addons/account_maturity_date_default/models/account_move.py
odoo/addons/account_maturity_date_default/models/account_move_line.py
odoo/addons/account_maturity_date_default/readme/CONTRIBUTORS.md
odoo/addons/account_maturity_date_default/readme/DESCRIPTION.md
odoo/addons/account_maturity_date_default/static/description/icon.png
odoo/addons/account_maturity_date_default/static/description/index.html
odoo/addons/account_maturity_date_default/tests/__init__.py
odoo/addons/account_maturity_date_default/tests/test_account_move.py
odoo_addon_account_maturity_date_default-18.0.1.0.0.4.dist-info/METADATA
odoo_addon_account_maturity_date_default-18.0.1.0.0.4.dist-info/WHEEL
odoo_addon_account_maturity_date_default-18.0.1.0.0.4.dist-info/top_level.txt
odoo_addon_account_maturity_date_default-18.0.1.0.0.4.dist-info/RECORD
